tests/__init__.py
upbitbox/__init__.py
upbitbox/exchanges.py
upbitbox/quotations.py
upbitbox/request_api.py
upbitbox/urls.py
upbitbox-0.0.1.dist-info/LICENSE
upbitbox-0.0.1.dist-info/METADATA
upbitbox-0.0.1.dist-info/WHEEL
upbitbox-0.0.1.dist-info/top_level.txt
upbitbox-0.0.1.dist-info/RECORD
