Metadata-Version: 2.1
Name: upbitbox
Version: 0.0.1
Summary: python wrapper for Upbit
Home-page: https://github.com/DK-Lite/upbitbox.git
Author: dk-lite
Author-email: kdk5go@gmail.com
License: UNKNOWN
Platform: UNKNOWN
Requires-Python: >=3.6
License-File: LICENSE
Requires-Dist: requests
Requires-Dist: pandas
Requires-Dist: PyJWT
Requires-Dist: PyYAML
